jupyterlab_jupytext/__init__.py
jupyterlab_jupytext/labextension/install.json
jupyterlab_jupytext/labextension/package.json
jupyterlab_jupytext/labextension/schemas/jupyterlab-jupytext/package.json.orig
jupyterlab_jupytext/labextension/schemas/jupyterlab-jupytext/plugin.json
jupyterlab_jupytext/labextension/static/48.4172aded109d990daa22.js
jupyterlab_jupytext/labextension/static/48.4172aded109d990daa22.js.LICENSE.txt
jupyterlab_jupytext/labextension/static/509.0926c6788335fe7dbdf8.js
jupyterlab_jupytext/labextension/static/720.639ed2b4892a443a19c6.js
jupyterlab_jupytext/labextension/static/remoteEntry.84740c0bf9a6442a86fd.js
jupyterlab_jupytext/labextension/static/style.js
jupyterlab_jupytext/labextension/static/third-party-licenses.json
jupytext/__init__.py
jupytext/__main__.py
jupytext/async_contentsmanager.py
jupytext/async_pairs.py
jupytext/cell_metadata.py
jupytext/cell_reader.py
jupytext/cell_to_text.py
jupytext/cli.py
jupytext/combine.py
jupytext/compare.py
jupytext/config.py
jupytext/doxygen.py
jupytext/formats.py
jupytext/header.py
jupytext/jupytext.py
jupytext/kernels.py
jupytext/languages.py
jupytext/magics.py
jupytext/metadata_filter.py
jupytext/myst.py
jupytext/paired_paths.py
jupytext/pairs.py
jupytext/pandoc.py
jupytext/pep8.py
jupytext/quarto.py
jupytext/reraise.py
jupytext/stringparser.py
jupytext/sync_contentsmanager.py
jupytext/sync_pairs.py
jupytext/version.py
jupytext_config/__init__.py
jupytext_config/__main__.py
jupytext_config/jupytext_config.py
jupytext_config/labconfig.py
jupytext-1.18.0.data/data/etc/jupyter/jupyter_notebook_config.d/jupytext.json
jupytext-1.18.0.data/data/etc/jupyter/jupyter_server_config.d/jupytext.json
jupytext-1.18.0.data/data/share/jupyter/labextensions/jupyterlab-jupytext/install.json
jupytext-1.18.0.data/data/share/jupyter/labextensions/jupyterlab-jupytext/package.json
jupytext-1.18.0.data/data/share/jupyter/labextensions/jupyterlab-jupytext/schemas/jupyterlab-jupytext/package.json.orig
jupytext-1.18.0.dist-info/METADATA
jupytext-1.18.0.dist-info/WHEEL
jupytext-1.18.0.dist-info/entry_points.txt
jupytext-1.18.0.dist-info/licenses/LICENSE
jupytext-1.18.0.dist-info/RECORD
