Metadata-Version: 2.4
Name: jupytext
Version: 1.18.0
Summary: Jupyter notebooks as Markdown documents, Julia, Python or R scripts
Project-URL: Homepage, https://github.com/mwouts/jupytext
Project-URL: Source Code, https://github.com/mwouts/jupytext
Project-URL: Documentation, https://jupytext.readthedocs.io
Author-email: Marc Wouts <marc.wouts@gmail.com>
License: MIT License
License-File: LICENSE
Classifier: Development Status :: 5 - Production/Stable
Classifier: Environment :: Console
Classifier: Framework :: Jupyter
Classifier: Framework :: Jupyter :: JupyterLab :: 4
Classifier: Framework :: Jupyter :: JupyterLab :: Extensions
Classifier: Framework :: Jupyter :: JupyterLab :: Extensions :: Prebuilt
Classifier: Intended Audience :: Developers
Classifier: Intended Audience :: Science/Research
Classifier: License :: OSI Approved :: MIT License
Classifier: Programming Language :: Python
Classifier: Programming Language :: Python :: 3
Classifier: Programming Language :: Python :: 3.9
Classifier: Programming Language :: Python :: 3.10
Classifier: Programming Language :: Python :: 3.11
Classifier: Programming Language :: Python :: 3.12
Classifier: Programming Language :: Python :: 3.13
Classifier: Programming Language :: Python :: 3.14
Classifier: Topic :: Text Processing :: Markup
Requires-Python: >=3.9
Requires-Dist: markdown-it-py>=1.0
Requires-Dist: mdit-py-plugins
Requires-Dist: nbformat
Requires-Dist: packaging
Requires-Dist: pyyaml
Requires-Dist: tomli; python_version < '3.11'
Provides-Extra: dev
Requires-Dist: autopep8; extra == 'dev'
Requires-Dist: black; extra == 'dev'
Requires-Dist: flake8; extra == 'dev'
Requires-Dist: gitpython; extra == 'dev'
Requires-Dist: ipykernel; extra == 'dev'
Requires-Dist: isort; extra == 'dev'
Requires-Dist: jupyter-fs[fs]>=1.0; extra == 'dev'
Requires-Dist: jupyter-server!=2.11; extra == 'dev'
Requires-Dist: nbconvert; extra == 'dev'
Requires-Dist: pre-commit; extra == 'dev'
Requires-Dist: pytest; extra == 'dev'
Requires-Dist: pytest-asyncio; extra == 'dev'
Requires-Dist: pytest-cov>=2.6.1; extra == 'dev'
Requires-Dist: pytest-randomly; extra == 'dev'
Requires-Dist: pytest-xdist; extra == 'dev'
Requires-Dist: sphinx; extra == 'dev'
Requires-Dist: sphinx-gallery>=0.8; extra == 'dev'
Provides-Extra: docs
Requires-Dist: myst-parser; extra == 'docs'
Requires-Dist: sphinx; extra == 'docs'
Requires-Dist: sphinx-copybutton; extra == 'docs'
Requires-Dist: sphinx-rtd-theme; extra == 'docs'
Provides-Extra: test
Requires-Dist: pytest; extra == 'test'
Requires-Dist: pytest-asyncio; extra == 'test'
Requires-Dist: pytest-randomly; extra == 'test'
Requires-Dist: pytest-xdist; extra == 'test'
Provides-Extra: test-cov
Requires-Dist: black; extra == 'test-cov'
Requires-Dist: ipykernel; extra == 'test-cov'
Requires-Dist: jupyter-server!=2.11; extra == 'test-cov'
Requires-Dist: nbconvert; extra == 'test-cov'
Requires-Dist: pytest; extra == 'test-cov'
Requires-Dist: pytest-asyncio; extra == 'test-cov'
Requires-Dist: pytest-cov>=2.6.1; extra == 'test-cov'
Requires-Dist: pytest-randomly; extra == 'test-cov'
Requires-Dist: pytest-xdist; extra == 'test-cov'
Provides-Extra: test-external
Requires-Dist: autopep8; extra == 'test-external'
Requires-Dist: black; extra == 'test-external'
Requires-Dist: flake8; extra == 'test-external'
Requires-Dist: gitpython; extra == 'test-external'
Requires-Dist: ipykernel; extra == 'test-external'
Requires-Dist: isort; extra == 'test-external'
Requires-Dist: jupyter-fs[fs]>=1.0; extra == 'test-external'
Requires-Dist: jupyter-server!=2.11; extra == 'test-external'
Requires-Dist: nbconvert; extra == 'test-external'
Requires-Dist: pre-commit; extra == 'test-external'
Requires-Dist: pytest; extra == 'test-external'
Requires-Dist: pytest-asyncio; extra == 'test-external'
Requires-Dist: pytest-randomly; extra == 'test-external'
Requires-Dist: pytest-xdist; extra == 'test-external'
Requires-Dist: sphinx; extra == 'test-external'
Requires-Dist: sphinx-gallery>=0.8; extra == 'test-external'
Provides-Extra: test-functional
Requires-Dist: black; extra == 'test-functional'
Requires-Dist: pytest; extra == 'test-functional'
Requires-Dist: pytest-asyncio; extra == 'test-functional'
Requires-Dist: pytest-randomly; extra == 'test-functional'
Requires-Dist: pytest-xdist; extra == 'test-functional'
Provides-Extra: test-integration
Requires-Dist: black; extra == 'test-integration'
Requires-Dist: ipykernel; extra == 'test-integration'
Requires-Dist: jupyter-server!=2.11; extra == 'test-integration'
Requires-Dist: nbconvert; extra == 'test-integration'
Requires-Dist: pytest; extra == 'test-integration'
Requires-Dist: pytest-asyncio; extra == 'test-integration'
Requires-Dist: pytest-randomly; extra == 'test-integration'
Requires-Dist: pytest-xdist; extra == 'test-integration'
Provides-Extra: test-ui
Requires-Dist: bash-kernel; extra == 'test-ui'
